{
  "user": [
    {
      "username": "Gaby",
      "password": "barrioconecta",
      "id": "ce10"
    }
  ],
  "service": [
    {
      "name": "Inglés",
      "image": "https://res.cloudinary.com/dgtkeuzft/image/upload/v1709057268/curso-ingles-ni%C3%B1os_kgypc2.jpg",
      "description": "Inglés nivel medio para niños",
      "price": "30€/hora",
      "category": "Básico",
      "id": "3987"
    },
    
    {
      "id": "430e",
      "name": "sandra",
      "description": "hfhfh",
      "image": "https://res.cloudinary.com/dgtkeuzft/image/upload/v1709226284/kvwg3h9pt0zlasnlihiv.jpg",
      "price": "30",
      "category": "Medio"
    },
    {
      "id": "bab4",
      "name": "cocina con niños",
      "description": "niños comiendo",
      "image": "https://res.cloudinary.com/dgtkeuzft/image/upload/v1709226488/bsmspnfb28fnkltbtlng.jpg",
      "price": "10",
      "category": "Medio"
    }
  ]
}